[
  {
    "id":5437,
    "name":"CIRIA",
    "stands":"S1836"
  },
  {
    "id":5086,
    "name":"HETAS Ltd",
    "stands":"N3000"
  },
  {
    "id":5398,
    "name":"NCS UK Limited",
    "stands":"S769"
  },
  {
    "id":4994,
    "name":"Neolux",
    "stands":"N1409"
  },
  {
    "id":5431,
    "name":"Plumb Center",
    "stands":"N2710"
  },
  {
    "id":5160,
    "name":"UK Green Building Council",
    "stands":"N540, N730"
  },
  {
    "id":5211,
    "name":"UK Rainwater Harvesting Association",
    "stands":"S1550"
  }
]